tensorsocket/__init__.py
tensorsocket/consumer.py
tensorsocket/heartbeat.py
tensorsocket/payload.py
tensorsocket/producer.py
tensorsocket-0.0.3.dist-info/LICENSE
tensorsocket-0.0.3.dist-info/WHEEL
tensorsocket-0.0.3.dist-info/METADATA
tensorsocket-0.0.3.dist-info/RECORD
