Metadata-Version: 2.1
Name: tensorsocket
Version: 0.0.3
Summary: Data loading orchestrator for separating loading and training into different processes, sharing data one-to-many and connected via TCP.
Author-email: Neil Kim Nielsen <neilkimn@protonmail.com>
Requires-Python: >=3.10.0
Classifier: License :: OSI Approved :: MIT License
Requires-Dist: pyzmq >= 25.0.0
Requires-Dist: tornado >= 6.0.0
Requires-Dist: torch >= 2.0.0
Project-URL: Home, https://github.com/Resource-Aware-Data-systems-RAD/tensorsocket
